[
  {
    "portugueseTitle": "20 000 Espécies de Abelhas",
    "originalTitle": "20.000 especies de abejas",
    "year": "2023"
  },
  {
    "portugueseTitle": "A Aventura (reposição)",
    "originalTitle": "L'avventura",
    "year": "1960"
  },
  {
    "portugueseTitle": "A Infância Nua (Ciclo Um Verão com Maurice Pialat)",
    "originalTitle": "L'Enfance nue",
    "year": "1969"
  },
  {
    "portugueseTitle": "A Lua Ascendeu (cópia restaurada - ciclo Kinuyo Tanaka)",
    "originalTitle": "Tsuki wa noborinu",
    "year": "1955"
  },
  {
    "portugueseTitle": "A Pequena Sereia",
    "originalTitle": "The Little Mermaid",
    "year": "2023"
  },
  {
    "portugueseTitle": "A Princesa Errante (cópia restaurada - ciclo Kinuyo Tanaka)",
    "originalTitle": "Ruten no ôhi",
    "year": "1960"
  },
  {
    "portugueseTitle": "A Rapariga da Mala",
    "originalTitle": "La ragazza con la valigia",
    "year": "1961"
  },
  {
    "portugueseTitle": "A Viagem do Papa Francisco",
    "originalTitle": "In viaggio",
    "year": "2022"
  },
  {
    "portugueseTitle": "A Vida Íntima de Um Casal (Ciclo Um Verão com Maurice Pialat)",
    "originalTitle": "La Gueule ouverte",
    "year": "1974"
  },
  {
    "portugueseTitle": "Alemanha, Ano Zero (versão digital restaurada)",
    "originalTitle": "Germania, Anno Zero",
    "year": "1948"
  },
  {
    "portugueseTitle": "Alguém Vai Amar Alguém",
    "originalTitle": "Mishehu Yohav Mishehu",
    "year": "2022"
  },
  {
    "portugueseTitle": "Ao Sol de Satanás (Ciclo Um Verão com Maurice Pialat)",
    "originalTitle": "Sous le soleil de Satan",
    "year": "1987"
  },
  {
    "portugueseTitle": "Aos Nossos Amores (Ciclo Um Verão com Maurice Pialat)",
    "originalTitle": "À nos amours",
    "year": "1983"
  },
  {
    "portugueseTitle": "As Aventuras de StarDog e TurboCat",
    "originalTitle": "StarDog and TurboCat",
    "year": "2019"
  },
  {
    "portugueseTitle": "Asteroid City",
    "originalTitle": "",
    "year": "2023"
  },
  {
    "portugueseTitle": "Barbie",
    "originalTitle": "",
    "year": "2023"
  },
  {
    "portugueseTitle": "Cobweb - Segredo Maldito",
    "originalTitle": "Cobweb",
    "year": "2023"
  },
  {
    "portugueseTitle": "Elemental",
    "originalTitle": "",
    "year": "2023"
  },
  {
    "portugueseTitle": "Escola de Coelhos: Missão Ovo Dourado",
    "originalTitle": "Die Häschenschule 2 – Der große Eierklau",
    "year": "2022"
  },
  {
    "portugueseTitle": "Eva (versão do realizador - reposição)",
    "originalTitle": "Eva",
    "year": "1962"
  },
  {
    "portugueseTitle": "Fica Connosco",
    "originalTitle": "Reste un peu",
    "year": "2022"
  },
  {
    "portugueseTitle": "Finalmente o Verão",
    "originalTitle": "Cet été-là",
    "year": "2023"
  },
  {
    "portugueseTitle": "Homem-Aranha: Através Do Aranhaverso",
    "originalTitle": "Spider-Man: Across the Spider-Verse",
    "year": "2023"
  },
  {
    "portugueseTitle": "Indiana Jones e o Marcador do Destino",
    "originalTitle": "Indiana Jones and the Dial of Destiny",
    "year": "2023"
  },
  {
    "portugueseTitle": "Insidious: A Porta Vermelha",
    "originalTitle": "Insidious: The Red Door",
    "year": "2023"
  },
  {
    "portugueseTitle": "Ladrões de Bicicletas (reposição)",
    "originalTitle": "Ladri di biciclette",
    "year": "1948"
  },
  {
    "portugueseTitle": "Loulou (Ciclo Um Verão com Maurice Pialat)",
    "originalTitle": "Loulou",
    "year": "1980"
  },
  {
    "portugueseTitle": "Mal Viver",
    "originalTitle": "",
    "year": "2023"
  },
  {
    "portugueseTitle": "Mamma Roma (Ciclo o Cinema Segundo Pasolini)",
    "originalTitle": "Mamma Roma",
    "year": "1962"
  },
  {
    "portugueseTitle": "Mansão Assombrada",
    "originalTitle": "Haunted Mansion",
    "year": "2023"
  },
  {
    "portugueseTitle": "Maya Nilo (Laura)",
    "originalTitle": "",
    "year": "2022"
  },
  {
    "portugueseTitle": "Meg 2: O Regresso do Tubarão Gigante",
    "originalTitle": "Meg 2: The Trench",
    "year": "2023"
  },
  {
    "portugueseTitle": "Missão: Impossível - Ajuste de Contas Parte Um",
    "originalTitle": "Mission: Impossible - Dead Reckoning Part One",
    "year": "2023"
  },
  {
    "portugueseTitle": "Nostalgia (Ciclo Andrei Tarkovsky)",
    "originalTitle": "Nostalghia",
    "year": "1983"
  },
  {
    "portugueseTitle": "O Amor (versão digital restaurada)",
    "originalTitle": "L'Amore",
    "year": "1948"
  },
  {
    "portugueseTitle": "O Medo (versão digital restaurada)",
    "originalTitle": "Non Credo Più All'amore (La Paura)",
    "year": "1954"
  },
  {
    "portugueseTitle": "O Milagre de Milão (reposição)",
    "originalTitle": "Miracolo a Milano",
    "year": "1951"
  },
  {
    "portugueseTitle": "O Miúdo (Ciclo Um Verão com Maurice Pialat)",
    "originalTitle": "Le Garçu",
    "year": "1995"
  },
  {
    "portugueseTitle": "Olha Que Três!",
    "originalTitle": "La vie pour de vrai",
    "year": "2023"
  },
  {
    "portugueseTitle": "Oppenheimer",
    "originalTitle": "",
    "year": "2023"
  },
  {
    "portugueseTitle": "Os Demónios do Meu Avô",
    "originalTitle": "",
    "year": "2022"
  },
  {
    "portugueseTitle": "Ovos de Ouro - Uma Aventura em África",
    "originalTitle": "Un rescate de huevitos",
    "year": "2021"
  },
  {
    "portugueseTitle": "Para Sempre Mulher (cópia restaurada - ciclo Kinuyo Tanaka)",
    "originalTitle": "Chibusa yo eien nare",
    "year": "1955"
  },
  {
    "portugueseTitle": "Passarinhos e Passarões (Ciclo o Cinema Segundo Pasolini)",
    "originalTitle": "Uccellacci e uccellini",
    "year": "1966"
  },
  {
    "portugueseTitle": "Polícia (Ciclo Um Verão com Maurice Pialat)",
    "originalTitle": "Police",
    "year": "1985"
  },
  {
    "portugueseTitle": "Pôr do Sol: O Mistério do Colar de São Cajó",
    "originalTitle": "O Mistério do Colar de São Cajó",
    "year": "2023"
  },
  {
    "portugueseTitle": "Primeiro Passa no Exame (Ciclo Um Verão com Maurice Pialat)",
    "originalTitle": "Passe ton bac d'abord",
    "year": "1978"
  },
  {
    "portugueseTitle": "Quando o Amor Acaba (Ciclo Um Verão com Maurice Pialat)",
    "originalTitle": "Nous ne vieillirons pas ensemble",
    "year": "1972"
  },
  {
    "portugueseTitle": "Roma, Cidade Aberta (versão digital restaurada)",
    "originalTitle": "Roma, Città Aperta",
    "year": "1945"
  },
  {
    "portugueseTitle": "Ruby - Kraken Adolescente",
    "originalTitle": "Ruby Gillman, Teenage Kraken",
    "year": "2023"
  },
  {
    "portugueseTitle": "Stromboli (versão digital restaurada)",
    "originalTitle": "Stromboli",
    "year": "1950"
  },
  {
    "portugueseTitle": "Super Mario: O Filme",
    "originalTitle": "The Super Mario Bros. Movie",
    "year": "2023"
  },
  {
    "portugueseTitle": "Trenque Lauquen (1.ª Parte)",
    "originalTitle": "Trenque Lauquen",
    "year": "2023"
  },
  {
    "portugueseTitle": "Trenque Lauquen (2.ª Parte)",
    "originalTitle": "Trenque Lauquen",
    "year": "2023"
  },
  {
    "portugueseTitle": "Trenque Lauquen",
    "originalTitle": "",
    "year": "2023"
  },
  {
    "portugueseTitle": "Tudo na Boa",
    "originalTitle": "No Hard Feelings",
    "year": "2023"
  },
  {
    "portugueseTitle": "Um Voo Altamente",
    "originalTitle": "Richard the Stork and the Mystery of the Great Jewel",
    "year": "2023"
  },
  {
    "portugueseTitle": "Van Gogh (Ciclo Um Verão com Maurice Pialat)",
    "originalTitle": "Van Gogh",
    "year": "1991"
  },
  {
    "portugueseTitle": "Velocidade Furiosa X",
    "originalTitle": "Fast X",
    "year": "2023"
  },
  {
    "portugueseTitle": "Viagem em Itália (versão digital restaurada)",
    "originalTitle": "Viaggio in Italia",
    "year": "1954"
  },
  {
    "portugueseTitle": "Viver Mal",
    "originalTitle": "",
    "year": "2023"
  }
]
